{
	"schemaVersion": 1,
	"id": "modtemplate",
	"version": "${version}",
	"name": "ReviversMC mod template",
	"description": "ReviversMC mod template",
	"authors": [
		"ReviversMC"
	],
	"contact": {
		"homepage": "https://www.curseforge.com/minecraft/mc-mods/modtemplate",
		"issues": "https://github.com/ReviversMC/modtemplate/issues",
		"sources": "https://github.com/ReviversMC/modtemplate"
	},
	"icon": "assets/modtemplate/icon.png",
	"license": "LGPL-3.0-or-later",
	"environment": "*",
	"entrypoints": {
		"modmenu": [
			"com.github.reviversmc.modtemplate.integrations.ModMenuIntegration"
		],
		"main": [
			"com.github.reviversmc.modtemplate.Mod"
		]
	},
	"depends": {
		"minecraft": ">=1.16",
		"fabricloader": ">=0.12.9",
		"modtemplate-compat-1-20": "*"
	}
}
